{
  "status": "INDUCED",
  "overall": 0.9390265486725664,
  "train_overall": 0.9508407079646017,
  "primary_accuracy": 1.0,
  "train_primary_accuracy": 1.0,
  "overall_floor": 0.75,
  "per_field": {
    "schemaVersion": 1.0,
    "gameId": 1.0,
    "seed": 1.0,
    "status": 1.0,
    "is_actionable": 1.0,
    "terminal.isTerminal": 1.0,
    "terminal.outcome": 1.0,
    "terminal.reason": 1.0,
    "game_state.score": 1.0,
    "game_state.level": 1.0,
    "game_state.completion_progress": 1.0,
    "game_state.player.x": 0.52,
    "game_state.player.y": 0.0,
    "game_state.player.z": 0.6,
    "game_state.player.vx": 1.0,
    "game_state.player.vy": 0.0,
    "game_state.player.vz": 1.0,
    "game_state.player.health": 1.0,
    "game_state.player.hunger": 1.0,
    "game_state.player.is_grounded": 0.92,
    "game_state.player.is_sprinting": 1.0,
    "game_state.player.is_in_water": 1.0,
    "game_state.player.is_underwater": 1.0,
    "game_state.player.is_locked": 1.0,
    "game_state.player.yaw": 1.0,
    "game_state.player.pitch": 1.0,
    "game_state.environment.world_seed": 1.0,
    "game_state.environment.day_count": 1.0,
    "game_state.environment.loaded_chunks": 1.0,
    "game_state.environment.player_context.block_x": 1.0,
    "game_state.environment.player_context.block_y": 0.22,
    "game_state.environment.player_context.block_z": 1.0,
    "game_state.environment.player_context.biome": 1.0,
    "game_state.environment.player_context.feet_block": 1.0,
    "game_state.environment.player_context.head_block": 1.0,
    "game_state.environment.player_context.block_below": 1.0,
    "game_state.environment.player_context.block_above": 1.0,
    "game_state.environment.player_context.surface_y": 1.0,
    "game_state.environment.player_context.depth_below_surface": 1.0,
    "game_state.environment.player_context.is_underground": 1.0,
    "game_state.environment.nearby_resources.radius_horizontal": 1.0,
    "game_state.environment.nearby_resources.radius_vertical": 1.0,
    "game_state.environment.nearby_resources.stone.count": 0.36,
    "game_state.environment.nearby_resources.stone.nearest_distance": 0.9,
    "game_state.environment.nearby_resources.stone.nearest_x": 0.96,
    "game_state.environment.nearby_resources.stone.nearest_y": 1.0,
    "game_state.environment.nearby_resources.stone.nearest_z": 0.96,
    "game_state.environment.nearby_resources.stone.nearest_dx": 1.0,
    "game_state.environment.nearby_resources.stone.nearest_dy": 1.0,
    "game_state.environment.nearby_resources.stone.nearest_dz": 0.96,
    "game_state.environment.nearby_resources.coal_ore.count": 0.36,
    "game_state.environment.nearby_resources.coal_ore.nearest_distance": 1.0,
    "game_state.environment.nearby_resources.coal_ore.nearest_x": 0.92,
    "game_state.environment.nearby_resources.coal_ore.nearest_y": 1.0,
    "game_state.environment.nearby_resources.coal_ore.nearest_z": 0.92,
    "game_state.environment.nearby_resources.coal_ore.nearest_dx": 0.92,
    "game_state.environment.nearby_resources.coal_ore.nearest_dy": 1.0,
    "game_state.environment.nearby_resources.coal_ore.nearest_dz": 0.92,
    "game_state.environment.nearby_resources.iron_ore.count": 0.36,
    "game_state.environment.nearby_resources.iron_ore.nearest_distance": 0.9,
    "game_state.environment.nearby_resources.iron_ore.nearest_x": 0.96,
    "game_state.environment.nearby_resources.iron_ore.nearest_y": 1.0,
    "game_state.environment.nearby_resources.iron_ore.nearest_z": 1.0,
    "game_state.environment.nearby_resources.iron_ore.nearest_dx": 1.0,
    "game_state.environment.nearby_resources.iron_ore.nearest_dy": 1.0,
    "game_state.environment.nearby_resources.iron_ore.nearest_dz": 0.96,
    "game_state.environment.targeted_block.exists": 1.0,
    "game_state.environment.targeted_block.x": 1.0,
    "game_state.environment.targeted_block.y": 1.0,
    "game_state.environment.targeted_block.z": 1.0,
    "game_state.environment.targeted_block.face": 1.0,
    "game_state.environment.targeted_block.distance": 1.0,
    "game_state.environment.targeted_block.block_type": 1.0,
    "game_state.environment.targeted_block.hardness": 1.0,
    "game_state.environment.targeted_block.harvest_tool": 1.0,
    "game_state.environment.targeted_block.selected_tool_type": 1.0,
    "game_state.environment.targeted_block.selected_tool_matches": 1.0,
    "game_state.environment.break_progress": 1.0,
    "game_state.entities": 1.0,
    "game_state.inventory.selected_slot": 1.0,
    "game_state.inventory.selected_item": 1.0,
    "game_state.inventory.selected_item_count": 1.0,
    "game_state.inventory.selected_tool_type": 1.0,
    "game_state.inventory.selected_tool_speed": 1.0,
    "game_state.inventory.item_counts.grass": 1.0,
    "game_state.inventory.item_counts.dirt": 1.0,
    "game_state.inventory.item_counts.stone": 1.0,
    "game_state.inventory.item_counts.wood_log": 1.0,
    "game_state.inventory.item_counts.leaves": 1.0,
    "game_state.inventory.item_counts.sand": 1.0,
    "game_state.inventory.item_counts.water": 1.0,
    "game_state.inventory.item_counts.bedrock": 1.0,
    "game_state.inventory.item_counts.wood_plank": 1.0,
    "game_state.inventory.item_counts.cobblestone": 1.0,
    "game_state.inventory.item_counts.coal_ore": 1.0,
    "game_state.inventory.item_counts.iron_ore": 1.0,
    "game_state.inventory.item_counts.gold_ore": 1.0,
    "game_state.inventory.item_counts.diamond_ore": 1.0,
    "game_state.inventory.item_counts.torch": 1.0,
    "game_state.inventory.item_counts.glass": 1.0,
    "game_state.inventory.item_counts.crafting_table": 1.0,
    "game_state.inventory.item_counts.snow": 1.0,
    "game_state.inventory.item_counts.cactus": 1.0,
    "game_state.inventory.item_counts.wooden_pickaxe": 1.0,
    "game_state.inventory.item_counts.wooden_axe": 1.0,
    "game_state.inventory.item_counts.wooden_sword": 1.0,
    "game_state.inventory.item_counts.wooden_shovel": 1.0,
    "game_state.inventory.item_counts.wooden_hoe": 1.0,
    "game_state.inventory.item_gains.grass": 1.0,
    "game_state.inventory.item_gains.dirt": 1.0,
    "game_state.inventory.item_gains.stone": 1.0,
    "game_state.inventory.item_gains.wood_log": 1.0,
    "game_state.inventory.item_gains.leaves": 1.0,
    "game_state.inventory.item_gains.sand": 1.0,
    "game_state.inventory.item_gains.water": 1.0,
    "game_state.inventory.item_gains.bedrock": 1.0,
    "game_state.inventory.item_gains.wood_plank": 1.0,
    "game_state.inventory.item_gains.cobblestone": 1.0,
    "game_state.inventory.item_gains.coal_ore": 1.0,
    "game_state.inventory.item_gains.iron_ore": 1.0,
    "game_state.inventory.item_gains.gold_ore": 1.0,
    "game_state.inventory.item_gains.diamond_ore": 1.0,
    "game_state.inventory.item_gains.torch": 1.0,
    "game_state.inventory.item_gains.glass": 1.0,
    "game_state.inventory.item_gains.crafting_table": 1.0,
    "game_state.inventory.item_gains.snow": 1.0,
    "game_state.inventory.item_gains.cactus": 1.0,
    "game_state.inventory.item_gains.wooden_pickaxe": 1.0,
    "game_state.inventory.item_gains.wooden_axe": 1.0,
    "game_state.inventory.item_gains.wooden_sword": 1.0,
    "game_state.inventory.item_gains.wooden_shovel": 1.0,
    "game_state.inventory.item_gains.wooden_hoe": 1.0,
    "metrics.primary_score": 1.0,
    "metrics.attempts": 1.0,
    "metrics.hp": 1.0,
    "metrics.items_total": 1.0,
    "metrics.items_unique": 1.0,
    "metrics.hotbar_occupied_slots": 1.0,
    "metrics.inventory_occupied_slots": 1.0,
    "metrics.held_selected_item_count": 1.0,
    "metrics.held_selected_item_type": 1.0,
    "metrics.selected_tool_type": 1.0,
    "metrics.selected_tool_speed": 1.0,
    "metrics.collected_net_total": 1.0,
    "metrics.collected_positive_total": 1.0,
    "metrics.day_count": 1.0,
    "metrics.loaded_chunks": 1.0,
    "metrics.break_progress": 1.0,
    "metrics.targeted_block_exists": 1.0,
    "metrics.targeted_block_type": 1.0,
    "metrics.targeted_block_distance": 1.0,
    "metrics.targeted_block_harvest_tool": 1.0,
    "metrics.selected_tool_matches_target": 1.0,
    "metrics.surface_y": 1.0,
    "metrics.depth_below_surface": 1.0,
    "metrics.is_underground": 1.0,
    "metrics.biome": 1.0,
    "metrics.nearby_stone_count": 0.36,
    "metrics.nearest_stone_distance": 0.9,
    "metrics.nearby_iron_ore_count": 0.36,
    "metrics.nearest_iron_ore_distance": 0.9,
    "debug.ui.is_main_menu_visible": 1.0,
    "debug.ui.is_pause_menu_visible": 1.0,
    "debug.ui.is_inventory_visible": 1.0,
    "debug.ui.is_click_to_play_visible": 1.0,
    "debug.ui.is_loading": 1.0,
    "debug.selected_stack.type": 1.0,
    "debug.selected_stack.count": 1.0,
    "debug.baseline_item_counts.grass": 1.0,
    "debug.baseline_item_counts.dirt": 1.0,
    "debug.baseline_item_counts.stone": 1.0,
    "debug.baseline_item_counts.wood_log": 1.0,
    "debug.baseline_item_counts.leaves": 1.0,
    "debug.baseline_item_counts.sand": 1.0,
    "debug.baseline_item_counts.water": 1.0,
    "debug.baseline_item_counts.bedrock": 1.0,
    "debug.baseline_item_counts.wood_plank": 1.0,
    "debug.baseline_item_counts.cobblestone": 1.0,
    "debug.baseline_item_counts.coal_ore": 1.0,
    "debug.baseline_item_counts.iron_ore": 1.0,
    "debug.baseline_item_counts.gold_ore": 1.0,
    "debug.baseline_item_counts.diamond_ore": 1.0,
    "debug.baseline_item_counts.torch": 1.0,
    "debug.baseline_item_counts.glass": 1.0,
    "debug.baseline_item_counts.crafting_table": 1.0,
    "debug.baseline_item_counts.snow": 1.0,
    "debug.baseline_item_counts.cactus": 1.0,
    "debug.baseline_item_counts.wooden_pickaxe": 1.0,
    "debug.baseline_item_counts.wooden_axe": 1.0,
    "debug.baseline_item_counts.wooden_sword": 1.0,
    "debug.baseline_item_counts.wooden_shovel": 1.0,
    "debug.baseline_item_counts.wooden_hoe": 1.0,
    "debug.last_reset_method": 1.0
  },
  "n_cases": 50,
  "iterations": 1,
  "threshold": 0.9,
  "train_size": 100,
  "holdout_size": 50
}
